bit_bind/__init__.py
bit_bind/api/__init__.py
bit_bind/api/bind.py
bit_bind-0.1.0.dist-info/DESCRIPTION.rst
bit_bind-0.1.0.dist-info/METADATA
bit_bind-0.1.0.dist-info/RECORD
bit_bind-0.1.0.dist-info/WHEEL
bit_bind-0.1.0.dist-info/metadata.json
bit_bind-0.1.0.dist-info/top_level.txt
