Metadata-Version: 2.0
Name: bit-bind
Version: 0.1.0
Summary: Bittrex SMS Notifier
Home-page: https://github.com/hthompson6/bit-bind
Author: Hunter Thompson
Author-email: thompson.grey.hunter@gmail.com
License: MIT
Keywords: sms bittrex
Platform: UNKNOWN
Classifier: Programming Language :: Python
Classifier: Programming Language :: Python :: 2.7
Classifier: Operating System :: OS Independent
Classifier: License :: OSI Approved :: MIT License
Classifier: Development Status :: 3 - Alpha
Requires-Dist: requests (>=2.18.1)
